<krpano>
	
	<!-- Import noce's sking -->
    <include url="../../assets/krpano/skin/noceskin.xml" />
	<!-- Override noce's skin 
    	<skin_settings 	
    		title="true"
    		thumbs_text="true"
 		/>  -->
	<!-- Import model plugin for schede -->
	<include url="../../assets/krpano/plugins/showtext.xml" />

	<!-- Import gyroscope plugin -->
     <plugin name="gyro" devices="html5" keep="true" url="../../assets/krpano/plugins/gyro2.js" enabled="true" camroll="true" friction="0.0"
        touch_mode="full" sensor_mode="1" softstart="0.5" autocalibration="false" />
        
	
	<scene name="scene_pison-artificiali" title="pison-artificiali" onstart="" thumburl="panos/pison-artificiali.tiles/thumb.jpg" lat="" lng="" heading="">

		<view hlookat="-55.0" vlookat="0.0" fovtype="MFOV" fov="120" maxpixelzoom="1.0" fovmin="70" fovmax="140" limitview="auto" />

		<preview url="panos/pison-artificiali.tiles/preview.jpg" />

		<image type="CUBE" multires="true" tilesize="512">
			<level tiledimagewidth="2176" tiledimageheight="2176">
				<cube url="panos/pison-artificiali.tiles/%s/l2/%v/l2_%s_%v_%h.jpg" />
			</level>
			<level tiledimagewidth="1152" tiledimageheight="1152">
				<cube url="panos/pison-artificiali.tiles/%s/l1/%v/l1_%s_%v_%h.jpg" />
			</level>
		</image>

	</scene>

	<scene name="scene_pison-gigapixel" title="pison-gigapixel" onstart="" thumburl="panos/pison-gigapixel.tiles/thumb.jpg" lat="" lng="" heading="">

		<view hlookat="0.0" vlookat="0.0" fovtype="MFOV" fov="120" maxpixelzoom="1.0" fovmin="70" fovmax="140" limitview="auto" />

		<preview url="panos/pison-gigapixel.tiles/preview.jpg" />

		<!--scheda-orso -->
        <hotspot name="scheda-orso-Trigger"
           ath="-10" atv="5"
           scale="0.6"
           vr="false"
           onclick="jscall(loadScheda('scheda-orso'));"           
           type="image" url="../../assets/images/element.png" keep="false" visible="true" enabled="true" handcursor="true" distorted="true" maskchildren="false" edge="center"  zoom="false"  rotate="0.0"  alpha="1.0" borderwidth="2" bordercolor="#0xAAAAAA"
        />

        <hotspot name="scheda-orso-TriggerLabel"
           html="L'Orso Bruno"
           ath="-10" atv="5"
           vr="false"
           oy="50"
           type="text" css="font-family:Arial; font-size:24px; color:#000000;" vcenter="false" padding="2" edge="center" distorted="true" renderer="webgl" wordwrap="true" bg="true" bgcolor="0xFFFFFF" bgalpha="0.5" bgborder="0" bgroundedge="0" bgshadow="" txtshadow="" mergedalpha="true" oversampling="1.0" mipmapping="false" onautosized=""
        /><!-- Fine scheda-orso -->

		<image type="CUBE" multires="true" tilesize="512">
			<level tiledimagewidth="7680" tiledimageheight="7680">
				<cube url="panos/pison-gigapixel.tiles/%s/l4/%v/l4_%s_%v_%h.jpg" />
			</level>
			<level tiledimagewidth="3840" tiledimageheight="3840">
				<cube url="panos/pison-gigapixel.tiles/%s/l3/%v/l3_%s_%v_%h.jpg" />
			</level>
			<level tiledimagewidth="1792" tiledimageheight="1792">
				<cube url="panos/pison-gigapixel.tiles/%s/l2/%v/l2_%s_%v_%h.jpg" />
			</level>
			<level tiledimagewidth="1024" tiledimageheight="1024">
				<cube url="panos/pison-gigapixel.tiles/%s/l1/%v/l1_%s_%v_%h.jpg" />
			</level>
		</image>
		<hotspot name="scene_pison-meledrio"
			 onclick="loadscene('scene_pison-meledrio', null, MERGE);"
			 ath="-125.0" atv="35.0"
			 scale="0.35"
			 rotate="0.0"
			type="image" url="../../assets/images/arrow.png" keep="false" visible="true" enabled="true" handcursor="true" distorted="true" maskchildren="false" edge="center" zoom="false" borderwidth="2" bordercolor="#0xAAAAAA" alpha="1.0"/>

		

	</scene>

	<scene name="scene_pison-meledrio" title="pison-meledrio" onstart="" thumburl="panos/pison-meledrio.tiles/thumb.jpg" lat="" lng="" heading="">

		<view hlookat="70.0" vlookat="20.0" fovtype="MFOV" fov="120" maxpixelzoom="1.0" fovmin="70" fovmax="140" limitview="auto" />

		<preview url="panos/pison-meledrio.tiles/preview.jpg" />


		<!--scheda-trota-marmorata -->
        <hotspot name="scheda-trota-marmorata-Trigger"
           ath="30" atv="15"
           scale="0.6"
           vr="false"
           onclick="jscall(loadScheda('scheda-trota-marmorata'));"           
           type="image" url="../../assets/images/element.png" keep="false" visible="true" enabled="true" handcursor="true" distorted="true" maskchildren="false" edge="center"  zoom="false"  rotate="0.0"  alpha="1.0" borderwidth="2" bordercolor="#0xAAAAAA"
        />

        <hotspot name="scheda-trota-marmorata-TriggerLabel"
           html="La trota marmorata"
           ath="30" atv="15"
           vr="false"
           oy="50"
           type="text" css="font-family:Arial; font-size:24px; color:#000000;" vcenter="false" padding="2" edge="center" distorted="true" renderer="webgl" wordwrap="true" bg="true" bgcolor="0xFFFFFF" bgalpha="0.5" bgborder="0" bgroundedge="0" bgshadow="" txtshadow="" mergedalpha="true" oversampling="1.0" mipmapping="false" onautosized=""
        /><!-- Fine scheda-trota-marmorata -->

		<image type="CUBE" multires="true" tilesize="512">
			<level tiledimagewidth="2176" tiledimageheight="2176">
				<cube url="panos/pison-meledrio.tiles/%s/l2/%v/l2_%s_%v_%h.jpg" />
			</level>
			<level tiledimagewidth="1152" tiledimageheight="1152">
				<cube url="panos/pison-meledrio.tiles/%s/l1/%v/l1_%s_%v_%h.jpg" />
			</level>
		</image>
		<hotspot name="scene_pison-gigapixel"
			 onclick="loadscene('scene_pison-gigapixel', null, MERGE);"
			 ath="-45.0" atv="-35.0"
			 scale="0.25"
			 rotate="0.0"
			type="image" url="../../assets/images/arrow.png" keep="false" visible="true" enabled="true" handcursor="true" distorted="true" maskchildren="false" edge="center" zoom="false" borderwidth="2" bordercolor="#0xAAAAAA" alpha="1.0"/>
		<hotspot name="scene_pison-canyon"
			 onclick="loadscene('scene_pison-canyon', null, MERGE);"
			 ath="40.0" atv="10.0"
			 scale="0.25"
			 rotate="0.0"
			type="image" url="../../assets/images/arrow.png" keep="false" visible="true" enabled="true" handcursor="true" distorted="true" maskchildren="false" edge="center" zoom="false" borderwidth="2" bordercolor="#0xAAAAAA" alpha="1.0"/>

		
	</scene>

	<scene name="scene_pison-canyon" title="pison-canyon" onstart="" thumburl="panos/pison-canyon.tiles/thumb.jpg" lat="" lng="" heading="">

		<view hlookat="0" vlookat="0.0" fovtype="MFOV" fov="120" maxpixelzoom="1.0" fovmin="70" fovmax="140" limitview="auto" />

		<preview url="panos/pison-canyon.tiles/preview.jpg" />

		<image type="CUBE" multires="true" tilesize="512">
			<level tiledimagewidth="2176" tiledimageheight="2176">
				<cube url="panos/pison-canyon.tiles/%s/l2/%v/l2_%s_%v_%h.jpg" />
			</level>
			<level tiledimagewidth="1152" tiledimageheight="1152">
				<cube url="panos/pison-canyon.tiles/%s/l1/%v/l1_%s_%v_%h.jpg" />
			</level>
		</image>
		<hotspot name="scene_pison-meledrio"
			 onclick="loadscene('scene_pison-meledrio', null, MERGE);"
			 ath="-165.0" atv="-15"
			 scale="0.25"
			 rotate="0.0"
			type="image" url="../../assets/images/arrow.png" keep="false" visible="true" enabled="true" handcursor="true" distorted="true" maskchildren="false" edge="center" zoom="false" borderwidth="2" bordercolor="#0xAAAAAA" alpha="1.0"/>

	</scene>
	
	
	<!-- start Actions-->
	<!-- startup action - load the first scene -->
		<action name="startup" autorun="onstart">
		loadscene(scene_pison-gigapixel, null, MERGE);
	</action>

	<action name="togglescheda" type="Javascript"><![CDATA[
		toggleScheda();
	]]></action>

	<!-- end Actions-->


</krpano>
